{
  "basics": {
    "name": "Nicholas Sebastian",
    "label": "Shidler Undergraduate Student",
    "picture": "https://techfolios.github.io/template/images/me.png",
    "email": "nfs37@hawaii.edu",
    "phone": "",
    "website": "https://Nicholas-Sebastian.github.io",
    "summary": "I am currently a Shidler Student planning to major in Business MIS. This is my 2nd year in Shidler and plan to graduate Spring 2023.",
    "location": {
      "address": "",
      "postalCode": "",
      "city": "Honolulu",
      "countryCode": "USA",
      "region": "Hawaii"
    },
    "profiles": [
      {
        "network": "github",
        "username": "Nicholas-Sebastian",
        "url": "http://github.com/Nicholas-Sebastian"
      },
      {
        "network": "linkedin",
        "username": "Nicholas Sebastian",
        "url": "http://linkedin.com/in/nicholas-sebastian-709109214"
      }
    ]
  },
  "interests": [
    {
      "name": "Data Analysis",
      "keywords": [
      ]
    },
    {
      "name": "Web-Design",
      "keywords": [
      ]
    },
    {
      "name": "Gaming",
      "keywords": [
      ]
    }
  ],
  "skills": [
    {
      "name": "Code",
      "level": "",
      "keywords": [
        "Java",
        "Javascript",        
      ]
    },
    {
      "name": "OS & Software",
      "level": "",
      "keywords": [
        "Windows",
        "Microsoft Word",
        "Microsoft PowerPoint",
        "Microsoft Excel",
        "Microsoft Access",
        "Git/GitHub",       
      ]
    }
  ],
  "education": [
    {
      "institution": "University of Hawaii, Honolulu, HI",
      "area": "Business MIS (expected Spring, 2023)",
      "studyType": "B.S.",
      "startDate": "2018-09-01",
      "endDate": "Present",
      "gpa": "",
      "courses": [
      ]
    }
  ],
  "work": [
    {
      "company": "Saint Louis High School Tsurichida Program",
      "position": " Guide, Supervisor",
      "website": "",
      "startDate": "2015",
      "endDate": "2018",
      "summary": "Invite, teach, and show Japanese International students in Saint Louis High School & Hawai'i",
      "highlights": [
        "Led International Student Program",
        "Teach and guide volunteer students of Saint Louis High School on the program",
        "Assisted teaching International Students"
      ]
    }
  ],
  "volunteer": [
    {
      "organization": "Saint Louis High School Tsuichida Program",
      "website": "",
      "position": "TA, ATA",
      "startDate": "2015",
      "endDate": "2018",
      "summary": "Invite, teach, and show Japanese International students in Saint Louis High School & Hawai'i",
      "highlights": [
        "Assisted in teaching International Students",
        "Hlped organize schedule and course content"
      ]
    },
    {
      "organization": "",
      "website": "",
      "position": "",
      "startDate": "",
      "endDate": "",
      "summary": "",
      "highlights": [
        "",
        "",
        ""
      ]
    }
  ],
  
  "references": [
    {
      "name": "Available upon request",
      "reference": ""
    }
  ]
}
